gameFunctions/__init__.py
gameFunctions/gameFunctions.py
gameFunctions-0.19.dist-info/METADATA
gameFunctions-0.19.dist-info/WHEEL
gameFunctions-0.19.dist-info/top_level.txt
gameFunctions-0.19.dist-info/RECORD
