Metadata-Version: 2.1
Name: gameFunctions
Version: 0.19
Summary: gameFunctions is a library to facilitate the creation of games, such as a dialog advance function and so on. OBS: this library starts with mixer of the pygame initialiced, so you couldn't worry with this.
Author: Caio Martins
Keywords: game,functions,games,gameFunctions,audiogame,audiogames
Requires-Dist: accessible-output2
Requires-Dist: pygame
Requires-Dist: pythonBgt
